ccao5193_mcp_helloworld/__init__.py
ccao5193_mcp_helloworld-0.1.0.dist-info/WHEEL
ccao5193_mcp_helloworld-0.1.0.dist-info/entry_points.txt
ccao5193_mcp_helloworld-0.1.0.dist-info/METADATA
ccao5193_mcp_helloworld-0.1.0.dist-info/RECORD
