Metadata-Version: 2.3
Name: ccao5193-mcp-helloworld
Version: 0.1.0
Summary: Add your description here
Author-email: 1213751162@qq.com
Requires-Dist: mcp[cli]>=1.25.0
Requires-Python: >=3.13.10
